Metadata-Version: 1.1
Name: pycoc
Version: 0.0.1
Summary: PyCoC - an easy to use COPASI API for python
Home-page: UNKNOWN
Author: Frank T. Bergmann
Author-email: frank.bergmann@bioquant.uni-heidelberg.de
License: Artistic-2.0
Keywords: copasi sbml systems biology
Platform: Windows
Platform: Linux
Platform: MacOS
Classifier: Topic :: Scientific/Engineering :: Bio-Informatics
Classifier: Development Status :: 3 - Alpha
Classifier: License :: OSI Approved :: Artistic License
Classifier: Intended Audience :: Science/Research
Classifier: Intended Audience :: Education
Classifier: Natural Language :: English
Classifier: Operating System :: MacOS :: MacOS X
Classifier: Operating System :: Microsoft :: Windows
Classifier: Operating System :: POSIX :: Linux
Classifier: Programming Language :: C++
Classifier: Programming Language :: Python :: 2
Classifier: Programming Language :: Python :: 2.7
Classifier: Programming Language :: Python :: 3
Classifier: Programming Language :: Python :: 3.5
Classifier: Programming Language :: Python :: 3.6
Classifier: Programming Language :: Python :: 3.7
Classifier: Programming Language :: Python :: 3.8
Classifier: Programming Language :: Python :: 3.9
Classifier: Programming Language :: Python :: Implementation :: CPython
Classifier: Programming Language :: Python :: Implementation :: PyPy
